README.rst
setup.py
stackimpact/__init__.py
stackimpact/agent.py
stackimpact/api_request.py
stackimpact/config.py
stackimpact/config_loader.py
stackimpact/frame.py
stackimpact/frame_cache.py
stackimpact/message_queue.py
stackimpact/metric.py
stackimpact/runtime.py
stackimpact/utils.py
stackimpact.egg-info/PKG-INFO
stackimpact.egg-info/SOURCES.txt
stackimpact.egg-info/dependency_links.txt
stackimpact.egg-info/top_level.txt
stackimpact/profilers/__init__.py
stackimpact/profilers/allocation_profiler.py
stackimpact/profilers/block_profiler.py
stackimpact/profilers/cpu_profiler.py
stackimpact/reporters/__init__.py
stackimpact/reporters/error_reporter.py
stackimpact/reporters/process_reporter.py
stackimpact/reporters/profile_reporter.py
stackimpact/reporters/span_reporter.py